{
  "date": "2026-03-15",
  "title": "2026-03-15 の日次ニュースダイジェスト",
  "summary": "5カテゴリ（IT / AI / 暗号通貨 / 時事・経済ニュース / 旅行）で当日ニュースを要約。",
  "sections": [
    {
      "id": "it",
      "name": "IT",
      "items": [
        {
          "title": "As browser wars heat up, Chrome adds new productivity features | TechCrunch",
          "summaryLines": [
            "As browser wars heat up, Chrome adds new productivity features | TechCrunchに関する最新動向です。",
            "概要: Split View, PDF annotations, and &#039;Save to Chrome&#039; features come to the Chrome browser.",
            "背景や今後の影響を把握するため、継続ウォッチが有効です。"
          ],
          "whyImportant": "開発生産性・運用コスト・セキュリティ要件に直結し、実装判断へ影響するため。",
          "source": "techcrunch.com",
          "link": "https://techcrunch.com/2026/02/19/as-browser-wars-heat-up-chrome-adds-new-productivity-features"
        },
        {
          "title": "There's a truly new browser coming in 2026, and everyone should know about it",
          "summaryLines": [
            "There's a truly new browser coming in 2026, and everyone should know about itに関する最新動向です。",
            "概要: It might just be the fresh start the web has been waiting for",
            "背景や今後の影響を把握するため、継続ウォッチが有効です。"
          ],
          "whyImportant": "開発生産性・運用コスト・セキュリティ要件に直結し、実装判断へ影響するため。",
          "source": "makeuseof.com",
          "link": "https://www.makeuseof.com/theres-new-browser-coming-in-2026-everyone-should-know-about-it/"
        },
        {
          "title": "Today’s Wordle Hints for March 15, 2026 - The New York Times",
          "summaryLines": [
            "Today’s Wordle Hints for March 15, 2026 - The New York Timesに関する最新動向です。",
            "概要: Scroll down for hints and conversation about the puzzle for Sunday, March 15, 2026.",
            "背景や今後の影響を把握するため、継続ウォッチが有効です。"
          ],
          "whyImportant": "開発生産性・運用コスト・セキュリティ要件に直結し、実装判断へ影響するため。",
          "source": "nytimes.com",
          "link": "https://www.nytimes.com/2026/03/14/crosswords/wordle-review-1730.html"
        },
        {
          "title": "Progressive Web App Technology Is Outpacing Traditional Android Development",
          "summaryLines": [
            "Progressive Web App Technology Is Outpacing Traditional Android Developmentに関する最新動向です。",
            "概要: For over a decade, the &quot;app vs. web&quot; debate had a clear winner on the Android platform: na…",
            "背景や今後の影響を把握するため、継続ウォッチが有効です。"
          ],
          "whyImportant": "開発生産性・運用コスト・セキュリティ要件に直結し、実装判断へ影響するため。",
          "source": "androidheadlines.com",
          "link": "https://androidheadlines.com/2026/03/progressive-web-app-technology-is-outpacing-traditional-android-development.html"
        }
      ]
    },
    {
      "id": "ai",
      "name": "AI",
      "items": [
        {
          "title": "Meta pushes AI model 'Avocado' rollout to May or later, NYT reports | Reuters",
          "summaryLines": [
            "Meta pushes AI model 'Avocado' rollout to May or later, NYT reports | Reutersに関する最新動向です。",
            "概要: Meta has postponed the release of its artificial intelligence model \"Avocado\" to at least May, from…",
            "背景や今後の影響を把握するため、継続ウォッチが有効です。"
          ],
          "whyImportant": "モデル性能だけでなく、供給網・規制・導入ROIの観点で事業インパクトが大きいため。",
          "source": "reuters.com",
          "link": "https://www.reuters.com/technology/meta-delays-rollout-new-ai-model-nyt-reports-2026-03-12/"
        },
        {
          "title": "Meta Delays Rollout of New A.I. Model After Performance Concerns - The New York Times",
          "summaryLines": [
            "Meta Delays Rollout of New A.I. Model After Performance Concerns - The New York Timesに関する最新動向です。",
            "概要: The tech giant pushed back the timeline after spending billions to be on the cutting edge of artific…",
            "背景や今後の影響を把握するため、継続ウォッチが有効です。"
          ],
          "whyImportant": "モデル性能だけでなく、供給網・規制・導入ROIの観点で事業インパクトが大きいため。",
          "source": "nytimes.com",
          "link": "https://www.nytimes.com/2026/03/12/technology/meta-avocado-ai-model-delayed.html"
        },
        {
          "title": "Apple introduces the new MacBook Air with M5 - Apple",
          "summaryLines": [
            "Apple introduces the new MacBook Air with M5 - Appleに関する最新動向です。",
            "概要: Apple today announced the new MacBook Air with M5, bringing exceptional performance and expanded AI…",
            "背景や今後の影響を把握するため、継続ウォッチが有効です。"
          ],
          "whyImportant": "モデル性能だけでなく、供給網・規制・導入ROIの観点で事業インパクトが大きいため。",
          "source": "apple.com",
          "link": "https://www.apple.com/newsroom/2026/03/apple-introduces-the-new-macbook-air-with-m5/"
        },
        {
          "title": "Meta delays release of new AI model on performance concerns- NYT By Investing.com",
          "summaryLines": [
            "Meta delays release of new AI model on performance concerns- NYT By Investing.comに関する最新動向です。",
            "概要: Meta delays release of new AI model on performance concerns- NYT",
            "背景や今後の影響を把握するため、継続ウォッチが有効です。"
          ],
          "whyImportant": "モデル性能だけでなく、供給網・規制・導入ROIの観点で事業インパクトが大きいため。",
          "source": "investing.com",
          "link": "https://www.investing.com/news/stock-market-news/meta-delays-release-of-new-ai-model-on-performance-concerns-nyt-4558756"
        }
      ]
    },
    {
      "id": "crypto",
      "name": "暗号通貨",
      "items": [
        {
          "title": "Bitcoin's early crash to $60,000 now looks like a warning for stocks",
          "summaryLines": [
            "Bitcoin's early crash to $60,000 now looks like a warning for stocksに関する最新動向です。",
            "概要: Bitcoin has once again acted as a leading indicator for risk assets, plunging sharply before the ong…",
            "背景や今後の影響を把握するため、継続ウォッチが有効です。"
          ],
          "whyImportant": "マクロ要因と資金フローの影響を受けやすく、短期ボラティリティ管理が重要なため。",
          "source": "coindesk.com",
          "link": "https://www.coindesk.com/markets/2026/03/13/bitcoin-crashed-first-now-stocks-follow-cementing-btc-s-lead-indicator-cred"
        },
        {
          "title": "Crypto: Trending News, Latest Updates, Analysis",
          "summaryLines": [
            "Crypto: Trending News, Latest Updates, Analysisに関する最新動向です。",
            "概要: See the latest on Crypto. From breaking news to in-depth reporting, Bloomberg tracks the full story…",
            "背景や今後の影響を把握するため、継続ウォッチが有効です。"
          ],
          "whyImportant": "マクロ要因と資金フローの影響を受けやすく、短期ボラティリティ管理が重要なため。",
          "source": "bloomberg.com",
          "link": "https://bloomberg.com/latest/crypto"
        },
        {
          "title": "Crypto bill hits new impasse, raising doubts over its future | Reuters",
          "summaryLines": [
            "Crypto bill hits new impasse, raising doubts over its future | Reutersに関する最新動向です。",
            "概要: Talks on landmark crypto legislation have hit a new impasse after banks said they could not back a c…",
            "背景や今後の影響を把握するため、継続ウォッチが有効です。"
          ],
          "whyImportant": "マクロ要因と資金フローの影響を受けやすく、短期ボラティリティ管理が重要なため。",
          "source": "reuters.com",
          "link": "https://reuters.com/business/finance/crypto-bill-hits-new-impasse-raising-doubts-over-its-future-2026-03-05"
        },
        {
          "title": "Crypto Market News Today: Tokenized Stocks Cross $1 Billion With a 2,900% Surge as Pepeto at $0.000000186 Builds the Exchange Where Tokenized Capital Trades",
          "summaryLines": [
            "Crypto Market News Today: Tokenized Stocks Cross $1 Billion With a 2,900% Surge as Pepeto at $0.000000186 Builds the Exchange Where Tokenized Capital Tradesに関する最新動向です。",
            "概要: Press release - TOKENWIRE - Crypto Market News Today: Tokenized Stocks Cross $1 Billion With a 2,900…",
            "背景や今後の影響を把握するため、継続ウォッチが有効です。"
          ],
          "whyImportant": "マクロ要因と資金フローの影響を受けやすく、短期ボラティリティ管理が重要なため。",
          "source": "openpr.com",
          "link": "https://openpr.com/news/4422554/crypto-market-news-today-tokenized-stocks-cross-1-billion-with"
        }
      ]
    },
    {
      "id": "economy",
      "name": "時事・経済ニュース",
      "items": [
        {
          "title": "Stocks slip, dollar strong as Iran conflict pushes oil prices higher | Reuters",
          "summaryLines": [
            "Stocks slip, dollar strong as Iran conflict pushes oil prices higher | Reutersに関する最新動向です。",
            "概要: Stocks fell and the U.S. dollar strengthened on Friday as uncertainty over the Iran war continued to…",
            "背景や今後の影響を把握するため、継続ウォッチが有効です。"
          ],
          "whyImportant": "金利・為替・関税などの変化が、企業業績と投資判断に広範囲で波及するため。",
          "source": "reuters.com",
          "link": "https://www.reuters.com/world/china/global-markets-wrapup-1-2026-03-13/"
        },
        {
          "title": "Trump seeks to close $1.6 trillion revenue gap with raft of new tariffs | AP News",
          "summaryLines": [
            "Trump seeks to close $1.6 trillion revenue gap with raft of new tariffs | AP Newsに関する最新動向です。",
            "概要: The Trump administration this week stepped up its ambitious effort to replace about $1.6 trillion in…",
            "背景や今後の影響を把握するため、継続ウォッチが有効です。"
          ],
          "whyImportant": "金利・為替・関税などの変化が、企業業績と投資判断に広範囲で波及するため。",
          "source": "apnews.com",
          "link": "https://apnews.com/article/tariffs-trump-trade-275f146dbc591bab1730a911e04aa8ea"
        },
        {
          "title": "Schwab Market Update | Charles Schwab",
          "summaryLines": [
            "Schwab Market Update | Charles Schwabに関する最新動向です。",
            "概要: Learn what&#x27;s trending before the opening bell with Schwab&#x27;s market open report. Find out a…",
            "背景や今後の影響を把握するため、継続ウォッチが有効です。"
          ],
          "whyImportant": "金利・為替・関税などの変化が、企業業績と投資判断に広範囲で波及するため。",
          "source": "schwab.com",
          "link": "https://www.schwab.com/learn/story/stock-market-update-open"
        },
        {
          "title": "What Are the Chances of a U.S. Recession in 2026? | The Motley Fool",
          "summaryLines": [
            "What Are the Chances of a U.S. Recession in 2026? | The Motley Foolに関する最新動向です。",
            "概要: The largest prediction market puts the odds of a recession at about 29%.",
            "背景や今後の影響を把握するため、継続ウォッチが有効です。"
          ],
          "whyImportant": "金利・為替・関税などの変化が、企業業績と投資判断に広範囲で波及するため。",
          "source": "fool.com",
          "link": "https://fool.com/investing/2026/03/13/what-are-the-chances-of-a-us-recession-in-2026"
        }
      ]
    },
    {
      "id": "travel",
      "name": "旅行",
      "items": [
        {
          "title": "China is rebuilding its grip on North Korea. Is Kim Jong Un ready to oblige? | Reuters",
          "summaryLines": [
            "China is rebuilding its grip on North Korea. Is Kim Jong Un ready to oblige? | Reutersに関する最新動向です。",
            "概要: Growing trade ties and new border infrastructure show Beijing is drawing Pyongyang back into its orb…",
            "背景や今後の影響を把握するため、継続ウォッチが有効です。"
          ],
          "whyImportant": "需要回復・為替・政策変更が、消費行動や移動コストに直接影響するため。",
          "source": "reuters.com",
          "link": "https://www.reuters.com/investigations/china-is-rebuilding-its-grip-north-korea-is-kim-jong-un-ready-oblige-2026-03-11/"
        },
        {
          "title": "Qatar Airways Updates Confirmed Flights For Friday To Tuesday (March 13 – 17, 2026) + Terms Change - LoyaltyLobby",
          "summaryLines": [
            "Qatar Airways Updates Confirmed Flights For Friday To Tuesday (March 13 – 17, 2026) + Terms Change - LoyaltyLobbyに関する最新動向です。",
            "概要: Qatar Airways has made slight updates to the schgedule it plans to operate Friday to Tuesday (March…",
            "背景や今後の影響を把握するため、継続ウォッチが有効です。"
          ],
          "whyImportant": "需要回復・為替・政策変更が、消費行動や移動コストに直接影響するため。",
          "source": "loyaltylobby.com",
          "link": "https://loyaltylobby.com/2026/03/13/qatar-airways-updates-confirmed-flights-for-friday-to-tuesday-march-13-17-2026-terms-change"
        },
        {
          "title": "Dubai Airport travel update: 11 major airlines issue latest advice for DXB passengers | Time Out Dubai",
          "summaryLines": [
            "Dubai Airport travel update: 11 major airlines issue latest advice for DXB passengers | Time Out Dubaiに関する最新動向です。",
            "概要: But some of the world's biggest airlines continue to adjust to the current situation, and several ro…",
            "背景や今後の影響を把握するため、継続ウォッチが有効です。"
          ],
          "whyImportant": "需要回復・為替・政策変更が、消費行動や移動コストに直接影響するため。",
          "source": "timeoutdubai.com",
          "link": "https://www.timeoutdubai.com/news/dxb-travel-advice-march-2026"
        },
        {
          "title": "U.S. Travel Alert: Southwest Ceases Flights at Chicago & Washington Airports June 4 — Airlines, Airport Hotels, and Tourism Boards Sound Alarm! - Travel And Tour World",
          "summaryLines": [
            "U.S. Travel Alert: Southwest Ceases Flights at Chicago & Washington Airports June 4 — Airlines, Airport Hotels, and Tourism Boards Sound Alarm! - Travel And Tour Worldに関する最新動向です。",
            "概要: Southwest Airlines has just dropped a bombshell that will shake up U.S. air travel starting June 4…",
            "背景や今後の影響を把握するため、継続ウォッチが有効です。"
          ],
          "whyImportant": "需要回復・為替・政策変更が、消費行動や移動コストに直接影響するため。",
          "source": "travelandtourworld.com",
          "link": "https://www.travelandtourworld.com/news/article/u-s-travel-alert-southwest-ceases-flights-at-chicago-washington-airports-june-4-airlines-airport-hotels-and-tourism-boards-sound-alarm/"
        }
      ]
    }
  ],
  "top3": [
    "IT：As browser wars heat up, Chrome adds new productivity features | TechCrunch",
    "AI：Meta pushes AI model 'Avocado' rollout to May or later, NYT reports | Reuters",
    "暗号通貨：Bitcoin's early crash to $60,000 now looks like a warning for stocks"
  ],
  "headlines": [
    {
      "title": "As browser wars heat up, Chrome adds new productivity features | TechCrunch",
      "source": "techcrunch.com",
      "link": "https://techcrunch.com/2026/02/19/as-browser-wars-heat-up-chrome-adds-new-productivity-features",
      "snippet": "As browser wars heat up, Chrome adds new productivity features | TechCrunchに関する最新動向です。 概要: Split View, PDF annotations, and &#039;Save to Chrome&#039; features come to the Chrome browser."
    },
    {
      "title": "There's a truly new browser coming in 2026, and everyone should know about it",
      "source": "makeuseof.com",
      "link": "https://www.makeuseof.com/theres-new-browser-coming-in-2026-everyone-should-know-about-it/",
      "snippet": "There's a truly new browser coming in 2026, and everyone should know about itに関する最新動向です。 概要: It might just be the fresh start the web has been waiting for"
    },
    {
      "title": "Today’s Wordle Hints for March 15, 2026 - The New York Times",
      "source": "nytimes.com",
      "link": "https://www.nytimes.com/2026/03/14/crosswords/wordle-review-1730.html",
      "snippet": "Today’s Wordle Hints for March 15, 2026 - The New York Timesに関する最新動向です。 概要: Scroll down for hints and conversation about the puzzle for Sunday, March 15, 2026."
    },
    {
      "title": "Progressive Web App Technology Is Outpacing Traditional Android Development",
      "source": "androidheadlines.com",
      "link": "https://androidheadlines.com/2026/03/progressive-web-app-technology-is-outpacing-traditional-android-development.html",
      "snippet": "Progressive Web App Technology Is Outpacing Traditional Android Developmentに関する最新動向です。 概要: For over a decade, the &quot;app vs. web&quot; debate had a clear winner on the Android platform: na…"
    },
    {
      "title": "Meta pushes AI model 'Avocado' rollout to May or later, NYT reports | Reuters",
      "source": "reuters.com",
      "link": "https://www.reuters.com/technology/meta-delays-rollout-new-ai-model-nyt-reports-2026-03-12/",
      "snippet": "Meta pushes AI model 'Avocado' rollout to May or later, NYT reports | Reutersに関する最新動向です。 概要: Meta has postponed the release of its artificial intelligence model \"Avocado\" to at least May, from…"
    },
    {
      "title": "Meta Delays Rollout of New A.I. Model After Performance Concerns - The New York Times",
      "source": "nytimes.com",
      "link": "https://www.nytimes.com/2026/03/12/technology/meta-avocado-ai-model-delayed.html",
      "snippet": "Meta Delays Rollout of New A.I. Model After Performance Concerns - The New York Timesに関する最新動向です。 概要: The tech giant pushed back the timeline after spending billions to be on the cutting edge of artific…"
    },
    {
      "title": "Apple introduces the new MacBook Air with M5 - Apple",
      "source": "apple.com",
      "link": "https://www.apple.com/newsroom/2026/03/apple-introduces-the-new-macbook-air-with-m5/",
      "snippet": "Apple introduces the new MacBook Air with M5 - Appleに関する最新動向です。 概要: Apple today announced the new MacBook Air with M5, bringing exceptional performance and expanded AI…"
    },
    {
      "title": "Meta delays release of new AI model on performance concerns- NYT By Investing.com",
      "source": "investing.com",
      "link": "https://www.investing.com/news/stock-market-news/meta-delays-release-of-new-ai-model-on-performance-concerns-nyt-4558756",
      "snippet": "Meta delays release of new AI model on performance concerns- NYT By Investing.comに関する最新動向です。 概要: Meta delays release of new AI model on performance concerns- NYT"
    },
    {
      "title": "Bitcoin's early crash to $60,000 now looks like a warning for stocks",
      "source": "coindesk.com",
      "link": "https://www.coindesk.com/markets/2026/03/13/bitcoin-crashed-first-now-stocks-follow-cementing-btc-s-lead-indicator-cred",
      "snippet": "Bitcoin's early crash to $60,000 now looks like a warning for stocksに関する最新動向です。 概要: Bitcoin has once again acted as a leading indicator for risk assets, plunging sharply before the ong…"
    },
    {
      "title": "Crypto: Trending News, Latest Updates, Analysis",
      "source": "bloomberg.com",
      "link": "https://bloomberg.com/latest/crypto",
      "snippet": "Crypto: Trending News, Latest Updates, Analysisに関する最新動向です。 概要: See the latest on Crypto. From breaking news to in-depth reporting, Bloomberg tracks the full story…"
    },
    {
      "title": "Crypto bill hits new impasse, raising doubts over its future | Reuters",
      "source": "reuters.com",
      "link": "https://reuters.com/business/finance/crypto-bill-hits-new-impasse-raising-doubts-over-its-future-2026-03-05",
      "snippet": "Crypto bill hits new impasse, raising doubts over its future | Reutersに関する最新動向です。 概要: Talks on landmark crypto legislation have hit a new impasse after banks said they could not back a c…"
    },
    {
      "title": "Crypto Market News Today: Tokenized Stocks Cross $1 Billion With a 2,900% Surge as Pepeto at $0.000000186 Builds the Exchange Where Tokenized Capital Trades",
      "source": "openpr.com",
      "link": "https://openpr.com/news/4422554/crypto-market-news-today-tokenized-stocks-cross-1-billion-with",
      "snippet": "Crypto Market News Today: Tokenized Stocks Cross $1 Billion With a 2,900% Surge as Pepeto at $0.000000186 Builds the Exchange Where Tokenized Capital Tradesに関する最新動向です。 概要: Press release - TOKENWIRE - Crypto Market News Today: Tokenized Stocks Cross $1 Billion With a 2,900…"
    },
    {
      "title": "Stocks slip, dollar strong as Iran conflict pushes oil prices higher | Reuters",
      "source": "reuters.com",
      "link": "https://www.reuters.com/world/china/global-markets-wrapup-1-2026-03-13/",
      "snippet": "Stocks slip, dollar strong as Iran conflict pushes oil prices higher | Reutersに関する最新動向です。 概要: Stocks fell and the U.S. dollar strengthened on Friday as uncertainty over the Iran war continued to…"
    },
    {
      "title": "Trump seeks to close $1.6 trillion revenue gap with raft of new tariffs | AP News",
      "source": "apnews.com",
      "link": "https://apnews.com/article/tariffs-trump-trade-275f146dbc591bab1730a911e04aa8ea",
      "snippet": "Trump seeks to close $1.6 trillion revenue gap with raft of new tariffs | AP Newsに関する最新動向です。 概要: The Trump administration this week stepped up its ambitious effort to replace about $1.6 trillion in…"
    },
    {
      "title": "Schwab Market Update | Charles Schwab",
      "source": "schwab.com",
      "link": "https://www.schwab.com/learn/story/stock-market-update-open",
      "snippet": "Schwab Market Update | Charles Schwabに関する最新動向です。 概要: Learn what&#x27;s trending before the opening bell with Schwab&#x27;s market open report. Find out a…"
    },
    {
      "title": "What Are the Chances of a U.S. Recession in 2026? | The Motley Fool",
      "source": "fool.com",
      "link": "https://fool.com/investing/2026/03/13/what-are-the-chances-of-a-us-recession-in-2026",
      "snippet": "What Are the Chances of a U.S. Recession in 2026? | The Motley Foolに関する最新動向です。 概要: The largest prediction market puts the odds of a recession at about 29%."
    },
    {
      "title": "China is rebuilding its grip on North Korea. Is Kim Jong Un ready to oblige? | Reuters",
      "source": "reuters.com",
      "link": "https://www.reuters.com/investigations/china-is-rebuilding-its-grip-north-korea-is-kim-jong-un-ready-oblige-2026-03-11/",
      "snippet": "China is rebuilding its grip on North Korea. Is Kim Jong Un ready to oblige? | Reutersに関する最新動向です。 概要: Growing trade ties and new border infrastructure show Beijing is drawing Pyongyang back into its orb…"
    },
    {
      "title": "Qatar Airways Updates Confirmed Flights For Friday To Tuesday (March 13 – 17, 2026) + Terms Change - LoyaltyLobby",
      "source": "loyaltylobby.com",
      "link": "https://loyaltylobby.com/2026/03/13/qatar-airways-updates-confirmed-flights-for-friday-to-tuesday-march-13-17-2026-terms-change",
      "snippet": "Qatar Airways Updates Confirmed Flights For Friday To Tuesday (March 13 – 17, 2026) + Terms Change - LoyaltyLobbyに関する最新動向です。 概要: Qatar Airways has made slight updates to the schgedule it plans to operate Friday to Tuesday (March…"
    },
    {
      "title": "Dubai Airport travel update: 11 major airlines issue latest advice for DXB passengers | Time Out Dubai",
      "source": "timeoutdubai.com",
      "link": "https://www.timeoutdubai.com/news/dxb-travel-advice-march-2026",
      "snippet": "Dubai Airport travel update: 11 major airlines issue latest advice for DXB passengers | Time Out Dubaiに関する最新動向です。 概要: But some of the world's biggest airlines continue to adjust to the current situation, and several ro…"
    },
    {
      "title": "U.S. Travel Alert: Southwest Ceases Flights at Chicago & Washington Airports June 4 — Airlines, Airport Hotels, and Tourism Boards Sound Alarm! - Travel And Tour World",
      "source": "travelandtourworld.com",
      "link": "https://www.travelandtourworld.com/news/article/u-s-travel-alert-southwest-ceases-flights-at-chicago-washington-airports-june-4-airlines-airport-hotels-and-tourism-boards-sound-alarm/",
      "snippet": "U.S. Travel Alert: Southwest Ceases Flights at Chicago & Washington Airports June 4 — Airlines, Airport Hotels, and Tourism Boards Sound Alarm! - Travel And Tour Worldに関する最新動向です。 概要: Southwest Airlines has just dropped a bombshell that will shake up U.S. air travel starting June 4…"
    }
  ],
  "meta": {
    "sourceMode": "brave",
    "categoryCount": 5,
    "itemCount": 20
  },
  "generatedAt": "2026-03-14T15:36:02.129838+00:00"
}